{
  "time": "palmeiras",
  "jogadores": [
    {
      "nome": "Weverton",
      "posicao": "GOL",
      "jogos": 56,
      "gols": 0,
      "assistencias": 0,
      "velocidade": 45,
      "chute": 25,
      "passe": 55,
      "drible": 30,
      "defesa": 86,
      "fisico": 82,
      "over_geral": 72,
      "idade": 37
    },
    {
      "nome": "Gustavo Gómez",
      "posicao": "ZAG",
      "jogos": 52,
      "gols": 3,
      "assistencias": 1,
      "velocidade": 60,
      "chute": 45,
      "passe": 62,
      "drible": 35,
      "defesa": 85,
      "fisico": 84,
      "over_geral": 74,
      "idade": 31
    },
    {
      "nome": "Murilo",
      "posicao": "ZAG",
      "jogos": 48,
      "gols": 1,
      "assistencias": 0,
      "velocidade": 68,
      "chute": 40,
      "passe": 60,
      "drible": 40,
      "defesa": 80,
      "fisico": 80,
      "over_geral": 72,
      "idade": 27
    },
    {
      "nome": "Piquerez",
      "posicao": "LAT",
      "jogos": 50,
      "gols": 2,
      "assistencias": 5,
      "velocidade": 78,
      "chute": 55,
      "passe": 75,
      "drible": 70,
      "defesa": 65,
      "fisico": 72,
      "over_geral": 70,
      "idade": 28
    },
    {
      "nome": "Giay",
      "posicao": "LAT",
      "jogos": 42,
      "gols": 1,
      "assistencias": 3,
      "velocidade": 75,
      "chute": 45,
      "passe": 70,
      "drible": 68,
      "defesa": 62,
      "fisico": 68,
      "over_geral": 66,
      "idade": 19
    },
    {
      "nome": "Aníbal Moreno",
      "posicao": "VOL",
      "jogos": 45,
      "gols": 1,
      "assistencias": 2,
      "velocidade": 65,
      "chute": 50,
      "passe": 75,
      "drible": 55,
      "defesa": 75,
      "fisico": 75,
      "over_geral": 70,
      "idade": 24
    },
    {
      "nome": "Richard Ríos",
      "posicao": "MEI",
      "jogos": 50,
      "gols": 3,
      "assistencias": 4,
      "velocidade": 75,
      "chute": 65,
      "passe": 78,
      "drible": 75,
      "defesa": 65,
      "fisico": 72,
      "over_geral": 73,
      "idade": 24
    },
    {
      "nome": "Raphael Veiga",
      "posicao": "MEI",
      "jogos": 45,
      "gols": 8,
      "assistencias": 5,
      "velocidade": 62,
      "chute": 78,
      "passe": 82,
      "drible": 70,
      "defesa": 50,
      "fisico": 65,
      "over_geral": 71,
      "idade": 30
    },
    {
      "nome": "Emiliano Martínez",
      "posicao": "MEI",
      "jogos": 40,
      "gols": 4,
      "assistencias": 3,
      "velocidade": 70,
      "chute": 60,
      "passe": 72,
      "drible": 68,
      "defesa": 55,
      "fisico": 65,
      "over_geral": 67,
      "idade": 23
    },
    {
      "nome": "Facundo Torres",
      "posicao": "PD",
      "jogos": 52,
      "gols": 12,
      "assistencias": 8,
      "velocidade": 80,
      "chute": 75,
      "passe": 72,
      "drible": 80,
      "defesa": 40,
      "fisico": 65,
      "over_geral": 75,
      "idade": 24
    },
    {
      "nome": "Estêvão",
      "posicao": "PD",
      "jogos": 48,
      "gols": 13,
      "assistencias": 5,
      "velocidade": 85,
      "chute": 72,
      "passe": 70,
      "drible": 82,
      "defesa": 35,
      "fisico": 60,
      "over_geral": 75,
      "idade": 17
    },
    {
      "nome": "Flaco López",
      "posicao": "ATA",
      "jogos": 42,
      "gols": 10,
      "assistencias": 4,
      "velocidade": 68,
      "chute": 78,
      "passe": 65,
      "drible": 68,
      "defesa": 40,
      "fisico": 75,
      "over_geral": 70,
      "idade": 24
    },
    {
      "nome": "Vitor Roque",
      "posicao": "ATA",
      "jogos": 40,
      "gols": 8,
      "assistencias": 3,
      "velocidade": 80,
      "chute": 75,
      "passe": 60,
      "drible": 75,
      "defesa": 35,
      "fisico": 72,
      "over_geral": 71,
      "idade": 20
    },
    {
      "nome": "Maurício",
      "posicao": "MEI",
      "jogos": 38,
      "gols": 3,
      "assistencias": 2,
      "velocidade": 72,
      "chute": 60,
      "passe": 70,
      "drible": 68,
      "defesa": 55,
      "fisico": 65,
      "over_geral": 66,
      "idade": 21
    },
    {
      "nome": "Allan",
      "posicao": "VOL",
      "jogos": 35,
      "gols": 0,
      "assistencias": 2,
      "velocidade": 65,
      "chute": 45,
      "passe": 72,
      "drible": 50,
      "defesa": 72,
      "fisico": 73,
      "over_geral": 67,
      "idade": 28
    },
    {
      "nome": "Felipe Anderson",
      "posicao": "MEI",
      "jogos": 33,
      "gols": 2,
      "assistencias": 3,
      "velocidade": 75,
      "chute": 65,
      "passe": 75,
      "drible": 72,
      "defesa": 50,
      "fisico": 65,
      "over_geral": 69,
      "idade": 32
    },
    {
      "nome": "Vanderlan",
      "posicao": "LAT",
      "jogos": 30,
      "gols": 0,
      "assistencias": 1,
      "velocidade": 78,
      "chute": 40,
      "passe": 65,
      "drible": 65,
      "defesa": 60,
      "fisico": 65,
      "over_geral": 64,
      "idade": 23
    },
    {
      "nome": "Bruno Fuchs",
      "posicao": "ZAG",
      "jogos": 28,
      "gols": 0,
      "assistencias": 0,
      "velocidade": 65,
      "chute": 40,
      "passe": 58,
      "drible": 35,
      "defesa": 76,
      "fisico": 78,
      "over_geral": 69,
      "idade": 25
    },
    {
      "nome": "Gabriel Menino",
      "posicao": "MEI",
      "jogos": 30,
      "gols": 1,
      "assistencias": 2,
      "velocidade": 65,
      "chute": 55,
      "passe": 72,
      "drible": 60,
      "defesa": 60,
      "fisico": 68,
      "over_geral": 64,
      "idade": 24
    },
    {
      "nome": "Marcos Rocha",
      "posicao": "LAT",
      "jogos": 25,
      "gols": 0,
      "assistencias": 1,
      "velocidade": 68,
      "chute": 40,
      "passe": 65,
      "drible": 50,
      "defesa": 65,
      "fisico": 68,
      "over_geral": 61,
      "idade": 32
    }
  ]
}